linear_cli/__init__.py
linear_cli/__main__.py
linear_cli/constants.py
linear_cli/api/__init__.py
linear_cli/api/auth.py
linear_cli/api/client.py
linear_cli/api/queries.py
linear_cli/api/auth/__init__.py
linear_cli/api/auth/core.py
linear_cli/api/auth/oauth.py
linear_cli/api/auth/storage.py
linear_cli/api/client/__init__.py
linear_cli/api/client/client.py
linear_cli/api/client/exceptions.py
linear_cli/api/client/utils.py
linear_cli/cli/__init__.py
linear_cli/cli/app.py
linear_cli/cli/formatters.py
linear_cli/cli/commands/__init__.py
linear_cli/cli/commands/auth.py
linear_cli/cli/commands/bulk.py
linear_cli/cli/commands/completion.py
linear_cli/cli/commands/config.py
linear_cli/cli/commands/interactive.py
linear_cli/cli/commands/issue.py
linear_cli/cli/commands/label.py
linear_cli/cli/commands/project.py
linear_cli/cli/commands/search.py
linear_cli/cli/commands/team.py
linear_cli/cli/commands/user.py
linear_cli/config/__init__.py
linear_cli/config/exceptions.py
linear_cli/config/manager.py
linear_cli/utils/__init__.py
linear_cli/utils/helpers.py
linear_cli/utils/performance.py
linearator-1.4.0.dist-info/licenses/LICENSE
linearator-1.4.0.dist-info/METADATA
linearator-1.4.0.dist-info/WHEEL
linearator-1.4.0.dist-info/entry_points.txt
linearator-1.4.0.dist-info/top_level.txt
linearator-1.4.0.dist-info/RECORD
