Metadata-Version: 2.4
Name: linearator
Version: 1.4.0
Summary: A comprehensive CLI tool for Linear issue management with advanced search, bulk operations, and team collaboration features
Author-email: Adil Alizada <adilalizade13@gmail.com>
License: MIT
Project-URL: Homepage, https://github.com/AdiKsOnDev/linearator
Project-URL: Repository, https://github.com/AdiKsOnDev/linearator.git
Project-URL: Bug Reports, https://github.com/AdiKsOnDev/linearator/issues
Project-URL: Feature Requests, https://github.com/AdiKsOnDev/linearator/issues/
Project-URL: Discussions, https://github.com/AdiKsOnDev/linearator/discussions
Project-URL: Changelog, https://github.com/AdiKsOnDev/linearator/blob/main/CHANGELOG.md
Project-URL: Release Notes, https://github.com/AdiKsOnDev/linearator/releases
Keywords: linear,cli,issue-tracker,project-management,workflow,automation,graphql,api-client,team-collaboration,bulk-operations
Classifier: Development Status :: 5 - Production/Stable
Classifier: Environment :: Console
Classifier: Intended Audience :: Developers
Classifier: Intended Audience :: End Users/Desktop
Classifier: License :: OSI Approved :: MIT License
Classifier: Natural Language :: English
Classifier: Operating System :: OS Independent
Classifier: Programming Language :: Python :: 3
Classifier: Programming Language :: Python :: 3.12
Classifier: Programming Language :: Python :: 3.13
Classifier: Topic :: Office/Business :: Scheduling
Classifier: Topic :: Software Development :: Bug Tracking
Classifier: Topic :: Software Development :: Libraries :: Python Modules
Classifier: Topic :: System :: Systems Administration
Classifier: Topic :: Utilities
Classifier: Typing :: Typed
Requires-Python: >=3.12
License-File: LICENSE
Requires-Dist: click>=8.1.0
Requires-Dist: gql[aiohttp]>=3.4.0
Requires-Dist: aiohttp>=3.8.0
Requires-Dist: pydantic>=2.0.0
Requires-Dist: keyring>=24.0.0
Requires-Dist: cryptography>=41.0.0
Requires-Dist: rich>=13.0.0
Requires-Dist: python-dotenv>=1.0.0
Requires-Dist: pyjwt>=2.8.0
Requires-Dist: httpx>=0.24.0
Requires-Dist: tomli>=2.0.1; python_version < "3.11"
Requires-Dist: tomli-w>=1.0.0
Provides-Extra: dev
Requires-Dist: pytest>=7.4.0; extra == "dev"
Requires-Dist: pytest-cov>=4.1.0; extra == "dev"
Requires-Dist: pytest-asyncio>=0.21.0; extra == "dev"
Requires-Dist: pytest-mock>=3.11.0; extra == "dev"
Requires-Dist: ruff>=0.0.280; extra == "dev"
Requires-Dist: mypy>=1.5.0; extra == "dev"
Requires-Dist: types-requests>=2.31.0; extra == "dev"
Requires-Dist: pre-commit>=3.3.0; extra == "dev"
Requires-Dist: responses>=0.23.0; extra == "dev"
Requires-Dist: aioresponses>=0.7.4; extra == "dev"
Requires-Dist: bandit>=1.7.5; extra == "dev"
Requires-Dist: safety>=2.0.0; extra == "dev"
Provides-Extra: docs
Requires-Dist: sphinx>=7.0.0; extra == "docs"
Requires-Dist: sphinx-autodoc-typehints>=1.24.0; extra == "docs"
Requires-Dist: sphinx-rtd-theme>=1.3.0; extra == "docs"
Requires-Dist: myst-parser>=2.0.0; extra == "docs"
Provides-Extra: test
Requires-Dist: pytest>=7.4.0; extra == "test"
Requires-Dist: pytest-cov>=4.1.0; extra == "test"
Requires-Dist: pytest-asyncio>=0.21.0; extra == "test"
Requires-Dist: pytest-mock>=3.11.0; extra == "test"
Requires-Dist: pytest-benchmark>=4.0.0; extra == "test"
Requires-Dist: responses>=0.23.0; extra == "test"
Requires-Dist: aioresponses>=0.7.4; extra == "test"
Dynamic: license-file
